maltest/__init__.py
maltest/maltest.py
maltest/utils.py
maltest/tests/.gitignore
maltest/tests/conftest.py
maltest/tests/test_arkime_api.py
maltest/tests/test_common_protocols.py
maltest/tests/test_connectivity.py
maltest/tests/test_detection_packages.py
maltest/tests/test_evtx.py
maltest/tests/test_mapi.py
maltest/tests/test_netbox.py
maltest/tests/test_nginx_access.py
maltest/tests/test_ot_protocols.py
maltest/tests/test_severity.py
maltest/tests/test_upstreams.py
maltest/virter/debian-13/fini/README.md
maltest/virter/debian-13/init/00-system.toml
maltest/virter/debian-13/init/01-apt-init.toml
maltest/virter/debian-13/init/02-docker.toml
maltest/virter/debian-13/init/03-podman.toml
maltest/virter/debian-13/init/README.md
maltest/virter/malcolm-fini/README.md
maltest/virter/malcolm-init/01-clone-install.toml
maltest/virter/malcolm-init/02-auth_setup.toml
maltest/virter/malcolm-init/03-pull.toml
maltest/virter/malcolm-init/99-reboot.toml
maltest/virter/malcolm-init/README.md
malcolm_test-0.13.1.dist-info/METADATA
malcolm_test-0.13.1.dist-info/WHEEL
malcolm_test-0.13.1.dist-info/entry_points.txt
malcolm_test-0.13.1.dist-info/licenses/LICENSE.txt
malcolm_test-0.13.1.dist-info/RECORD
