Metadata-Version: 2.4
Name: malcolm-test
Version: 0.13.1
Summary: A package for performing tests against a Malcolm system
Project-URL: Homepage, https://github.com/idaholab/malcolm-test
Project-URL: Issues, https://github.com/idaholab/malcolm-test/issues
Project-URL: Artifacts, https://github.com/idaholab/malcolm-test-artifacts
Project-URL: PyPI, https://pypi.org/project/malcolm-test/
Author-email: Seth Grover <mero.mero.guero@gmail.com>
License-File: LICENSE.txt
Classifier: License :: OSI Approved :: Apache Software License
Classifier: Operating System :: POSIX :: Linux
Classifier: Programming Language :: Python :: 3
Requires-Python: >=3.11
Requires-Dist: beautifulsoup4==4.14.2
Requires-Dist: elasticsearch-dsl==8.18.0
Requires-Dist: elasticsearch==8.18.0
Requires-Dist: mmguero>=2.0.3
Requires-Dist: opensearch-py==3.0.0
Requires-Dist: petname==2.6
Requires-Dist: psutil==7.1.2
Requires-Dist: pytest==8.4.2
Requires-Dist: python-magic==0.4.27
Requires-Dist: requests==2.32.5
Requires-Dist: stream-unzip==0.0.99
Requires-Dist: tomli-w==1.2.0
Requires-Dist: tomli==2.3.0
